mgnet/__init__.py
mgnet/model.py
mgnet/py.typed
mgnet-0.1.2.dist-info/WHEEL
mgnet-0.1.2.dist-info/METADATA
mgnet-0.1.2.dist-info/RECORD
