Metadata-Version: 2.4
Name: mgnet
Version: 0.1.2
Summary: Multigrid Neural Network implemented in PyTorch
Author: AKJ7
Author-email: AKJ7 <akj123429@gmail.com>
License-Expression: MIT
Classifier: Programming Language :: Python
Classifier: Programming Language :: Python :: 3.10
Classifier: Intended Audience :: Developers
Classifier: Intended Audience :: Education
Classifier: Intended Audience :: Science/Research
Classifier: Topic :: Scientific/Engineering
Classifier: Topic :: Scientific/Engineering :: Mathematics
Classifier: Topic :: Scientific/Engineering :: Artificial Intelligence
Classifier: Topic :: Software Development
Classifier: Topic :: Software Development :: Libraries
Classifier: Topic :: Software Development :: Libraries :: Python Modules
Requires-Dist: torch>=2.10.0
Requires-Python: >=3.10
Project-URL: Homepage, https://github.com/AKJ7/mgnet
